jikoku/__init__.py
jikoku/config.py
jikoku/models.py
jikoku/scheduler.py
jikoku/time.py
jikoku/utils.py
jikoku/visuals.py
jikoku-0.0.1.dist-info/METADATA
jikoku-0.0.1.dist-info/WHEEL
jikoku-0.0.1.dist-info/RECORD
