Metadata-Version: 2.1
Name: jikoku
Version: 0.0.1
Summary: Python utility to generate working timetables from general schedule data.
Author: Anton L
Author-email: takeoischifan@github.com
Requires-Python: >=3.11,<4.0
Classifier: Programming Language :: Python :: 3
Classifier: Programming Language :: Python :: 3.11
